geoagrodatalab/__init__.py
geoagrodatalab/common.py
geoagrodatalab/geoagrodatalab.py
geoagrodatalab/language.py
geoagrodatalab/translatations.py
geoagrodatalab-1.1.0.dist-info/licenses/LICENSE
geoagrodatalab-1.1.0.dist-info/METADATA
geoagrodatalab-1.1.0.dist-info/WHEEL
geoagrodatalab-1.1.0.dist-info/entry_points.txt
geoagrodatalab-1.1.0.dist-info/top_level.txt
geoagrodatalab-1.1.0.dist-info/RECORD
