Metadata-Version: 2.4
Name: geoagrodatalab
Version: 1.1.0
Summary: Python Package for GeoAgro DataLab
Author-email: Thomas Varela <tvarela@geoagro.com>, Nicolas Soria <nsoria@geoagro.com>, Mariano Bonelli <mbonelli@geoagro.com>
License: MIT License
Project-URL: Homepage, https://github.com/GeoagrobyTEK/geoagrodatalab
Keywords: geoagrodatalab
Classifier: Intended Audience :: Developers
Classifier: License :: OSI Approved :: MIT License
Classifier: Natural Language :: English
Classifier: Programming Language :: Python :: 3.8
Classifier: Programming Language :: Python :: 3.9
Classifier: Programming Language :: Python :: 3.10
Classifier: Programming Language :: Python :: 3.11
Classifier: Programming Language :: Python :: 3.12
Requires-Python: >=3.8
License-File: LICENSE
Provides-Extra: all
Requires-Dist: geoagrodatalab[extra]; extra == "all"
Provides-Extra: extra
Requires-Dist: pandas; extra == "extra"
Dynamic: license-file
